DESCRIPTION.rst
LICENSE
MANIFEST.in
README.md
requirements.txt
setup.cfg
setup.py
nurbs/BSpline.py
nurbs/CPGen.py
nurbs/NURBS.py
nurbs/__init__.py
nurbs/_convert.py
nurbs/_exchange.py
nurbs/_linalg.py
nurbs/_operations.py
nurbs/_tessellate.py
nurbs/_utilities.py
nurbs/_voxelize.py
nurbs/abstract.py
nurbs/compatibility.py
nurbs/construct.py
nurbs/control_points.py
nurbs/convert.py
nurbs/elements.py
nurbs/evaluators.py
nurbs/exceptions.py
nurbs/exchange.py
nurbs/exchange_vtk.py
nurbs/fitting.py
nurbs/freeform.py
nurbs/functools_lru_cache.py
nurbs/helpers.py
nurbs/knotvector.py
nurbs/linalg.py
nurbs/multi.py
nurbs/operations.py
nurbs/ray.py
nurbs/shortcuts.py
nurbs/sweeping.py
nurbs/tessellate.py
nurbs/trimming.py
nurbs/utilities.py
nurbs/vis.py
nurbs/voxelize.py
nurbs.egg-info/PKG-INFO
nurbs.egg-info/SOURCES.txt
nurbs.egg-info/dependency_links.txt
nurbs.egg-info/not-zip-safe
nurbs.egg-info/top_level.txt
nurbs/visualization/VisMPL.py
nurbs/visualization/VisPlotly.py
nurbs/visualization/VisVTK.py
nurbs/visualization/__init__.py
nurbs/visualization/vtk_helpers.py
tests/test_compatibility.py
tests/test_convert.py
tests/test_curve.py
tests/test_evaluate.py
tests/test_helpers.py
tests/test_linalg.py
tests/test_ray.py
tests/test_read_write.py
tests/test_surface.py
tests/test_surfgen.py
tests/test_utils.py
tests/test_visualization.py