Metadata-Version: 2.1
Name: nurbs
Version: 0.1
Summary: Object-oriented B-Spline and NURBS evaluation library
Home-page: https://github.com/Dessia-tech/nurbs
Author: Onur Rauf Bingol & Dessia Technologies
Author-email: root@dessia.tech
License: MIT
Project-URL: Documentation, https://github.com/Dessia-tech/nurbs/doc
Project-URL: Source, https://github.com/Dessia-tech/nurbs
Project-URL: Tracker, https://github.com/Dessia-tech/nurbs/issues
Keywords: NURBS B-Spline curve surface CAD modeling visualization surface-generator
Platform: UNKNOWN
Classifier: Development Status :: 5 - Production/Stable
Classifier: Intended Audience :: Science/Research
Classifier: License :: OSI Approved :: MIT License
Classifier: Topic :: Scientific/Engineering :: Mathematics
Classifier: Topic :: Scientific/Engineering :: Visualization
Classifier: Operating System :: OS Independent
Classifier: Programming Language :: Python :: 3
Classifier: Programming Language :: Python :: 3.8
License-File: LICENSE
